Metadata-Version: 1.1
Name: pytpmutils
Version: 0.1.2
Summary: Basic TPM python utils for Linux
Home-page: https://github.com/ph4r05/py-tpm-utils
Author: Dusan Klinec (ph4r05)
Author-email: dusan.klinec@gmail.com
License: 
